Metadata-Version: 2.4
Name: jkp-depth-anything-v2
Version: 0.1.1
Summary: Depth Anything V2: Robust Monocular Depth Estimation
Author: Lihe Yang, Bingyi Kang, Zilong Huang, Zhen Zhao, Xiaogang Xu, Jiashi Feng, Hengshuang Zhao
License-Expression: Apache-2.0 AND CC-BY-NC-4.0
Project-URL: Homepage, https://github.com/DepthAnything/Depth-Anything-V2
Project-URL: Issues, https://github.com/DepthAnything/Depth-Anything-V2/issues
Classifier: Programming Language :: Python :: 3
Classifier: Operating System :: OS Independent
Classifier: Topic :: Scientific/Engineering :: Artificial Intelligence
Requires-Python: >=3.6
License-File: LICENSE
Requires-Dist: gradio
Requires-Dist: gradio_imageslider
Requires-Dist: matplotlib
Requires-Dist: opencv-python
Requires-Dist: torch
Requires-Dist: torchvision
Dynamic: license-file
